kwekash/__main__.py
kwekash-2.1.2.dist-info/licenses/LICENSE
kwekash-2.1.2.dist-info/METADATA
kwekash-2.1.2.dist-info/WHEEL
kwekash-2.1.2.dist-info/entry_points.txt
kwekash-2.1.2.dist-info/top_level.txt
kwekash-2.1.2.dist-info/RECORD
